openexcept/__init__.py
openexcept/core.py
openexcept/easy.py
openexcept/handlers.py
openexcept/configs/config.yaml
openexcept/configs/config_local_fs.yaml
openexcept/configs/config_local_url.yaml
openexcept/embeddings/base.py
openexcept/embeddings/openai_embedding.py
openexcept/embeddings/sentence_transformers.py
openexcept/embeddings/tests/test_sentence_transformer.py
openexcept/scripts/cleanup_local_fs_storage.py
openexcept/storage/base.py
openexcept/storage/qdrant.py
openexcept/storage/tests/test_qdrant.py
openexcept-0.1.0.dist-info/LICENSE
openexcept-0.1.0.dist-info/METADATA
openexcept-0.1.0.dist-info/WHEEL
openexcept-0.1.0.dist-info/top_level.txt
openexcept-0.1.0.dist-info/RECORD
