Metadata-Version: 2.1
Name: openexcept
Version: 0.1.0
Summary: Automatic exception grouping using AI
Home-page: https://github.com/OpenExcept/OpenExcept
Author: OpenExcept
Author-email: OpenExcept <ai.observability.eng@gmail.com>
License: AGPLv3
Classifier: Programming Language :: Python :: 3
Classifier: License :: OSI Approved :: GNU Affero General Public License v3
Classifier: Operating System :: OS Independent
Requires-Python: >=3.7
License-File: LICENSE
Requires-Dist: fastapi>=0.95.1
Requires-Dist: openai==1.51.2
Requires-Dist: qdrant-client==1.12.0
Requires-Dist: requests==2.30.0
Requires-Dist: sentence-transformers==3.2.0
Requires-Dist: huggingface-hub>=0.20.0
Requires-Dist: uvicorn==0.22.0
Provides-Extra: dev
Requires-Dist: pytest==7.3.1; extra == "dev"
Requires-Dist: requests==2.30.0; extra == "dev"
Requires-Dist: docker-compose==1.29.2; extra == "dev"
